pvml/__init__.py
pvml/agent.py
pvml/agent_session.py
pvml/audit.py
pvml/client.py
pvml/datasource.py
pvml/entities.py
pvml/group.py
pvml/llm.py
pvml/mcp.py
pvml/policy.py
pvml/pvml_http_client.py
pvml/routes.py
pvml/schema_relation.py
pvml/util.py
pvml/view.py
pvml/workspace.py
pvml/workspace_user.py
pvml/connector/__init__.py
pvml/connector/base.py
pvml/connector/bigquery.py
pvml/connector/postgres.py
pvml_sdk-0.2.5.dist-info/METADATA
pvml_sdk-0.2.5.dist-info/WHEEL
pvml_sdk-0.2.5.dist-info/top_level.txt
pvml_sdk-0.2.5.dist-info/RECORD
