Metadata-Version: 2.4
Name: pvml-sdk
Version: 0.2.5
Summary: Python SDK library for PVML apis
Author-email: Shlomi Pakado <shlomi.pakado@pvml.com>
Project-URL: Homepage, https://github.com/PVML-ltd/pvml-sdk-python
Requires-Python: >=3.11
Requires-Dist: aiohttp~=3.11.13
Requires-Dist: PyJWT~=2.10.1
Requires-Dist: nest-asyncio~=1.6.0
Requires-Dist: requests~=2.32.4
Requires-Dist: sseclient-py~=1.8.0
